{"cameraMode":{"drawMode":0,"name":"Shaded","section":"Shading Mode"},"sceneLighting":false,"audioPlay":false,"sceneViewState":{"m_AlwaysRefresh":false,"showFog":true,"showSkybox":true,"showFlares":true,"showImageEffects":true,"showParticleSystems":true,"showVisualEffectGraphs":true,"m_FxEnabled":true},"in2DMode":false,"pivot":{"x":203.1383514404297,"y":12.397806167602539,"z":854.626220703125},"rotation":{"x":0.02670285664498806,"y":-0.9408944249153137,"z":0.07637804001569748,"w":0.3289124369621277},"size":8.417908668518067,"orthographic":true}