{"cameraMode":{"drawMode":0,"name":"Shaded","section":"Shading Mode"},"sceneLighting":false,"audioPlay":false,"sceneViewState":{"m_AlwaysRefresh":false,"showFog":true,"showSkybox":true,"showFlares":true,"showImageEffects":true,"showParticleSystems":true,"showVisualEffectGraphs":true,"m_FxEnabled":true},"in2DMode":false,"pivot":{"x":405.69366455078127,"y":-11.11639404296875,"z":690.8297119140625},"rotation":{"x":-0.07894282042980194,"y":0.805148184299469,"z":-0.11011284589767456,"w":-0.5774964690208435},"size":482.12384033203127,"orthographic":false}